{"noiseKey":{"private":{"type":"Buffer","data":"eDra9svjlwfjFd6ST6oIEq4IvCP4a0Rg0PIFoFFPxks="},"public":{"type":"Buffer","data":"lsU+lx2poxXRg5AvMHh2p9QH0z6hF6AesLp6pTLjjCs="}},"pairingEphemeralKeyPair":{"private":{"type":"Buffer","data":"2Llv7hfag5LkBnilVQEQ8lqOflFuBBnDDq91KOqSBEE="},"public":{"type":"Buffer","data":"/1I+ZYLh0swNGPwyjj9Oeh43dwFSKmUKzgAKhBtwKQ8="}},"signedIdentityKey":{"private":{"type":"Buffer","data":"sBEPtFil6DngfA9ZlHmmFPMDp+b/SxisbFMNRzzG9Es="},"public":{"type":"Buffer","data":"p138pNbs3/iUCq9rahBrY2kZZxo7c+/BDaMOmRKn32A="}},"signedPreKey":{"keyPair":{"private":{"type":"Buffer","data":"MFWChg8BDdZdIPdSeS795a3EA+ZLO1vT3XyGcWggQ2Q="},"public":{"type":"Buffer","data":"aDlkbLniEzxSQS4O/cO+JDvu/KzP/IDD8Ec1xujofBw="}},"signature":{"type":"Buffer","data":"ZmbTqXP15812vL96CiUcRUJI2fo9I0r647n3/OaeizORNqBt8tYEyjglSfW5KzfYZeDzQiuHjRaTEPy7YHWKhQ=="},"keyId":1},"registrationId":70,"advSecretKey":"nwZAr/4e1qA3ionMmN6JnWUfsBCMWZJ6QumI0HQByb8=","processedHistoryMessages":[{"key":{"remoteJid":"601154299771@s.whatsapp.net","fromMe":true,"id":"3A6EDF3AAE2A98B7322E"},"messageTimestamp":1715765511},{"key":{"remoteJid":"601154299771@s.whatsapp.net","fromMe":true,"id":"3AA8731C970C0A9246AE"},"messageTimestamp":1715765514},{"key":{"remoteJid":"601154299771@s.whatsapp.net","fromMe":true,"id":"3A4FA09A76E3037CBAF7"},"messageTimestamp":1715765522},{"key":{"remoteJid":"601154299771@s.whatsapp.net","fromMe":true,"id":"3AC5B889C8FD309FF670"},"messageTimestamp":1715765533},{"key":{"remoteJid":"601154299771@s.whatsapp.net","fromMe":true,"id":"3A3CD746057B1F278149"},"messageTimestamp":1715765538},{"key":{"remoteJid":"601154299771@s.whatsapp.net","fromMe":true,"id":"3A18F865DC01B0988DE3"},"messageTimestamp":1715765544},{"key":{"remoteJid":"601154299771@s.whatsapp.net","fromMe":true,"id":"3AC40EF939D7CD4A8342"},"messageTimestamp":1715765555},{"key":{"remoteJid":"601154299771@s.whatsapp.net","fromMe":true,"id":"3A7FD2666C5D3F9C5CC8"},"messageTimestamp":1715765555},{"key":{"remoteJid":"601154299771@s.whatsapp.net","fromMe":true,"id":"3A3F36A4B323FBECAF0B"},"messageTimestamp":1715765561},{"key":{"remoteJid":"601154299771@s.whatsapp.net","fromMe":true,"id":"3A31A636C9AD5485B967"},"messageTimestamp":1715765572},{"key":{"remoteJid":"601154299771@s.whatsapp.net","fromMe":true,"id":"3A8FB89C649E55AF6BDA"},"messageTimestamp":1715765572},{"key":{"remoteJid":"601154299771@s.whatsapp.net","fromMe":true,"id":"3A183887B9673B10EEF1"},"messageTimestamp":1715765577},{"key":{"remoteJid":"601154299771@s.whatsapp.net","fromMe":true,"id":"3A70C0CBA37900989A0C"},"messageTimestamp":1715765588},{"key":{"remoteJid":"601154299771@s.whatsapp.net","fromMe":true,"id":"3AB4C331A2B0B4E0256D"},"messageTimestamp":1715765588},{"key":{"remoteJid":"601154299771@s.whatsapp.net","fromMe":true,"id":"3ADCF7308708A82D72D7"},"messageTimestamp":1715765594},{"key":{"remoteJid":"601154299771@s.whatsapp.net","fromMe":true,"id":"3AEFBC7C3D183E36AD03"},"messageTimestamp":1715765604},{"key":{"remoteJid":"601154299771@s.whatsapp.net","fromMe":true,"id":"3A9FC9928E77AECFA8BD"},"messageTimestamp":1715765604},{"key":{"remoteJid":"601154299771@s.whatsapp.net","fromMe":true,"id":"3AEFDCBA5140527E4CEA"},"messageTimestamp":1715765606},{"key":{"remoteJid":"601154299771@s.whatsapp.net","fromMe":true,"id":"3A945C7ACF7394A464B7"},"messageTimestamp":1715765607},{"key":{"remoteJid":"601154299771@s.whatsapp.net","fromMe":true,"id":"3AA1EAA8AF59B1552A10"},"messageTimestamp":1715765616},{"key":{"remoteJid":"601154299771@s.whatsapp.net","fromMe":true,"id":"3A157DEC577B7BDC68DE"},"messageTimestamp":1715765627},{"key":{"remoteJid":"601154299771@s.whatsapp.net","fromMe":true,"id":"3A4A2B9DF0FAC93B6DE4"},"messageTimestamp":1715765629},{"key":{"remoteJid":"601154299771@s.whatsapp.net","fromMe":true,"id":"3A0D9C5C3E22000820C9"},"messageTimestamp":1715765629}],"nextPreKeyId":31,"firstUnuploadedPreKeyId":31,"accountSyncCounter":1,"accountSettings":{"unarchiveChats":false},"deviceId":"UH1zXquDTEK94WHM0dDj1A","phoneId":"b822528e-42e2-4530-be6f-21cf599774bf","identityId":{"type":"Buffer","data":"p1kdaQNiW1502PBs1SNtGPDjKrM="},"registered":false,"backupToken":{"type":"Buffer","data":"ozLWb70Gj6GrMdcxx39pq+Kd+ac="},"registration":{},"account":{"details":"CPb1w5cOEP2BkrIGGAEgACgA","accountSignatureKey":"gyP0lCZQcYCTVNLpazFqhzw+2V1kpPKE3bT3tYXbbUE=","accountSignature":"vILJDmjv4OrB9Q40cGV0rOawp0usa5ktgZi18NVDPZQ12mTmQQzTnD9P0fW6I0Q+ak8CkcKbroXgsSAHhPL2CQ==","deviceSignature":"Vw2qd5OSD5ESPxnCp9C2PaZ8mdbW8QvC/TS4ScrFuMJaLfZhXsBE7TDxHUV3u+uHPWMyEixa76DmrHqBNrNfjw=="},"me":{"id":"601154299771:14@s.whatsapp.net","name":"‼️JGN PM NO BOT‼️","jid":"601154299771@s.whatsapp.net","lid":"183189180014731:14@lid"},"signalIdentities":[{"identifier":{"name":"601154299771:14@s.whatsapp.net","deviceId":0},"identifierKey":{"type":"Buffer","data":"BYMj9JQmUHGAk1TS6Wsxaoc8PtldZKTyhN2097WF221B"}}],"platform":"iphone","lastAccountSyncTimestamp":1715765507,"myAppStateKeyId":"AAAAAN9d"}
